pcbdraw/__init__.py
pcbdraw/_version.py
pcbdraw/convert.py
pcbdraw/convert_common.py
pcbdraw/convert_unix.py
pcbdraw/convert_windows.py
pcbdraw/mdrenderer.py
pcbdraw/pcbnew_common.py
pcbdraw/plot.py
pcbdraw/populate.py
pcbdraw/renderer.py
pcbdraw/ui.py
pcbdraw/unit.py
pcbdraw/resources/defaultKiCadSettings/3d_viewer.json
pcbdraw/resources/defaultKiCadSettings/user_colors.json
pcbdraw/resources/footprints/.git
pcbdraw/resources/footprints/LICENCE
pcbdraw/resources/footprints/README.md
pcbdraw/resources/footprints/Eagle-export/1X01.svg
pcbdraw/resources/footprints/Eagle-export/1X02.svg
pcbdraw/resources/footprints/Eagle-export/1X05.svg
pcbdraw/resources/footprints/Eagle-export/1X08.svg
pcbdraw/resources/footprints/Eagle-export/1X12.svg
pcbdraw/resources/footprints/Eagle-export/1X14.svg
pcbdraw/resources/footprints/Eagle-export/2X01.svg
pcbdraw/resources/footprints/Eagle-export/2X02.svg
pcbdraw/resources/footprints/Eagle-export/2X03.svg
pcbdraw/resources/footprints/Eagle-export/2X06.svg
pcbdraw/resources/footprints/Eagle-export/2X12.svg
pcbdraw/resources/footprints/Eagle-export/2X14.svg
pcbdraw/resources/footprints/Eagle-export/78XXS.svg
pcbdraw/resources/footprints/Eagle-export/ARDUINOR3-BPLACE.svg
pcbdraw/resources/footprints/Eagle-export/C0402.svg
pcbdraw/resources/footprints/Eagle-export/C0603.svg
pcbdraw/resources/footprints/Eagle-export/CHIP-LED0603.svg
pcbdraw/resources/footprints/Eagle-export/CHIPLED_0603.svg
"pcbdraw/resources/footprints/Eagle-export/E5-10,5.svg"
pcbdraw/resources/footprints/Eagle-export/ESP-WROOM-32.svg
"pcbdraw/resources/footprints/Eagle-export/MKDSN1,5%2f2-5,08.svg"
pcbdraw/resources/footprints/Eagle-export/R0603.svg
pcbdraw/resources/footprints/Eagle-export/SOD123.svg
pcbdraw/resources/footprints/Eagle-export/SOT23.svg
pcbdraw/resources/footprints/Eagle-export/TACTM-35N-F.svg
pcbdraw/resources/footprints/Eagle-export/USB-MICRO-B-BOTTOM-MOLEX.svg
pcbdraw/resources/footprints/KiCAD-base/Button_Switch_THT/SW_PUSH_6mm.svg
PcbDraw-1.1.2.dist-info/LICENSE
PcbDraw-1.1.2.dist-info/METADATA
PcbDraw-1.1.2.dist-info/WHEEL
PcbDraw-1.1.2.dist-info/entry_points.txt
PcbDraw-1.1.2.dist-info/top_level.txt
PcbDraw-1.1.2.dist-info/RECORD
