Metadata-Version: 2.1
Name: PcbDraw
Version: 1.1.2
Summary: Utility to produce nice looking drawings of KiCAD boards
Home-page: https://github.com/yaqwsx/PcbDraw
Author: Jan Mrázek
Author-email: email@honzamrazek.cz
License: UNKNOWN
Platform: UNKNOWN
Classifier: Programming Language :: Python :: 3
Classifier: License :: OSI Approved :: MIT License
Classifier: Operating System :: OS Independent
Requires-Python: >=3.7
Provides-Extra: dev
License-File: LICENSE
